O2Utils/O2Utils.py
O2Utils/__init__.py
robotframework_o2utils-0.0.4.dist-info/LICENSE.txt
robotframework_o2utils-0.0.4.dist-info/METADATA
robotframework_o2utils-0.0.4.dist-info/WHEEL
robotframework_o2utils-0.0.4.dist-info/top_level.txt
robotframework_o2utils-0.0.4.dist-info/RECORD
